pymessages/__init__.py
pymessages/_tools.py
pymessages/client.py
pymessages/service.py
pymessages/tests/__init__.py
pymessages/tests/test_dummy.py
pymessages-0.2.dist-info/METADATA
pymessages-0.2.dist-info/WHEEL
pymessages-0.2.dist-info/top_level.txt
pymessages-0.2.dist-info/RECORD
