Metadata-Version: 2.1
Name: pymessages
Version: 0.2
Summary: 📱 SMS gateway using your own phone!
Home-page: http://github.com/shivamsn97/pymessages
Author: Shivam Saini
Author-email: shivamsn97@gmail.com
License: ISC
Keywords: python sms-api sms-gateway google-messages
Platform: UNKNOWN
Classifier: Development Status :: 3 - Alpha
Classifier: License :: OSI Approved :: ISC License (ISCL)
Classifier: Programming Language :: Python :: 3.8
Classifier: Topic :: Software Development :: Libraries
Requires-Dist: pyppeteer
Requires-Dist: pyee
